test_package_tufskjywfa/__init__.py
test_package_tufskjywfa/choice.py
test_package_tufskjywfa-2020.1.10.dist-info/WHEEL
test_package_tufskjywfa-2020.1.10.dist-info/METADATA
test_package_tufskjywfa-2020.1.10.dist-info/RECORD
