Metadata-Version: 2.1
Name: test-package-tufskjywfa
Version: 2020.1.10
Summary: Small test library.
Author: Abc
Author-email: nr4809+26fip69foy9ec@sharklasers.com
Requires-Python: >=3.6,<4.0
Classifier: Programming Language :: Python :: 3
Classifier: Programming Language :: Python :: 3.6
Classifier: Programming Language :: Python :: 3.7
Classifier: Programming Language :: Python :: 3.8
Classifier: Programming Language :: Python :: 3.9
